dwrappr/__init__.py
dwrappr/dataset.py
dwrappr/filehandler.py
dwrappr/generators.py
dwrappr/timekeeper.py
dwrappr/utils.py
dwrappr-1.0.16.dist-info/licenses/LICENSE
dwrappr-1.0.16.dist-info/METADATA
dwrappr-1.0.16.dist-info/WHEEL
dwrappr-1.0.16.dist-info/top_level.txt
dwrappr-1.0.16.dist-info/RECORD
