Metadata-Version: 2.4
Name: dwrappr
Version: 1.0.16
Summary: A lightweight and extensible Python package for managing data, tailored for researchers working with structured data.
Author-email: Nils Klasen <likeable.versed-78@icloud.com>
License-Expression: MIT
Project-URL: Homepage, https://git-ce.rwth-aachen.de/kls/dwrappr
Project-URL: Documentation, https://dwrappr-725c08.pages.git-ce.rwth-aachen.de/
Project-URL: Issues, https://git-ce.rwth-aachen.de/kls/dwrappr/-/issues
Classifier: Programming Language :: Python :: 3.9
Classifier: Programming Language :: Python :: 3.10
Classifier: Programming Language :: Python :: 3.11
Classifier: Programming Language :: Python :: 3.12
Classifier: Operating System :: OS Independent
Requires-Python: <4,>=3.9
License-File: LICENSE
Requires-Dist: numpy>=2.0.0
Requires-Dist: pandas>=2.0.0
Requires-Dist: pyyaml>=6.0.0
Requires-Dist: joblib>=1.5.0
Requires-Dist: scikit-learn>=1.6.0
Dynamic: license-file
